nogi/__init__.py
nogi/client.py
nogi-0.2.0.dist-info/METADATA
nogi-0.2.0.dist-info/WHEEL
nogi-0.2.0.dist-info/entry_points.txt
nogi-0.2.0.dist-info/licenses/LICENSE
nogi-0.2.0.dist-info/RECORD
