Metadata-Version: 2.3
Name: nogi
Version: 0.2.0
Summary: Audit any running python process.
Project-URL: Homepage, https://github.com/4383/nogi
Project-URL: History, https://github.com/4383/nogi/blob/main/CHANGELOG.md
Project-URL: Sponsor, https://github.com/sponsors/4383
Project-URL: Tracker, https://github.com/4383/nogi/issues
Project-URL: Source, https://github.com/4383/nogi
Author-email: Hervé Beraud <herveberaud.pro@gmail.com>
License: MIT
License-File: LICENSE
Classifier: Development Status :: 3 - Alpha
Classifier: Environment :: Console
Classifier: Intended Audience :: Developers
Classifier: License :: OSI Approved :: MIT License
Classifier: Operating System :: OS Independent
Classifier: Programming Language :: Python
Classifier: Programming Language :: Python :: 3
Classifier: Programming Language :: Python :: 3.9
Classifier: Programming Language :: Python :: 3.10
Classifier: Programming Language :: Python :: 3.11
Classifier: Programming Language :: Python :: 3.12
Classifier: Topic :: Security
Classifier: Topic :: Sociology
Classifier: Topic :: Software Development
Requires-Python: >=3.8
Requires-Dist: pyzmq
Provides-Extra: dev
Requires-Dist: black; extra == 'dev'
Requires-Dist: build; extra == 'dev'
Requires-Dist: commitizen; extra == 'dev'
Requires-Dist: isort; extra == 'dev'
Requires-Dist: pip-tools; extra == 'dev'
Requires-Dist: pre-commit; extra == 'dev'
Requires-Dist: twine; extra == 'dev'
